kiko/__init__.py
kiko/app.py
kiko/cli.py
kiko/commands/__init__.py
kiko/commands/basic.py
kiko/commands/chat.py
kiko/runtime/__init__.py
kiko/runtime/command_spec.py
kiko/runtime/context.py
kiko/runtime/project.py
kiko/runtime/renderer.py
kiko/runtime/session.py
kiko/runtime/session_state.py
kiko/runtime/session_store.py
kiko/runtime/settings.py
kiko/runtime/version.py
kiko/ui/__init__.py
kiko/ui/completion.py
kiko/ui/components.py
kiko-0.1.0.dist-info/licenses/LICENSE
kiko-0.1.0.dist-info/WHEEL
kiko-0.1.0.dist-info/entry_points.txt
kiko-0.1.0.dist-info/METADATA
kiko-0.1.0.dist-info/RECORD
